RSBCLI.py
rsbcli-0.2.9.dist-info/entry_points.txt
rsbcli-0.2.9.dist-info/LICENSE
rsbcli-0.2.9.dist-info/WHEEL
rsbcli-0.2.9.dist-info/METADATA
rsbcli-0.2.9.dist-info/RECORD
