Metadata-Version: 2.1
Name: rsbcli
Version: 0.2.9
Summary: A RAM saving cli to run web applications. Update 0.2.9: New presets. 
Home-page: https://github.com/AvanindraC/RSB
License: MIT
Keywords: RSBCLI
Author: Avanindra Chakraborty
Author-email: avanindra.d2.chakraborty@gmail.com
Requires-Python: >=3.8,<4.0
Classifier: License :: OSI Approved :: MIT License
Classifier: Operating System :: OS Independent
Classifier: Programming Language :: Python :: 3
Classifier: Programming Language :: Python :: 3.6
Classifier: Programming Language :: Python :: 3.7
Classifier: Programming Language :: Python :: 3.8
Classifier: Programming Language :: Python :: 3.9
Requires-Dist: PyQt5 (>=5.15.4,<6.0.0)
Requires-Dist: PyQtWebEngine (>=5.15.4,<6.0.0)
Requires-Dist: click (>=8.0.1,<9.0.0)
Project-URL: Repository, https://github.com/AvanindraC/RSB
